celo_mcp/__init__.py
celo_mcp/server.py
celo_mcp/blockchain_data/__init__.py
celo_mcp/blockchain_data/client.py
celo_mcp/blockchain_data/models.py
celo_mcp/blockchain_data/service.py
celo_mcp/config/Election.json
celo_mcp/config/Validators.json
celo_mcp/config/__init__.py
celo_mcp/config/contracts.py
celo_mcp/config/settings.py
celo_mcp/contracts/__init__.py
celo_mcp/contracts/models.py
celo_mcp/contracts/service.py
celo_mcp/governance/__init__.py
celo_mcp/governance/formatting.py
celo_mcp/governance/models.py
celo_mcp/governance/service.py
celo_mcp/nfts/__init__.py
celo_mcp/nfts/models.py
celo_mcp/nfts/service.py
celo_mcp/staking/__init__.py
celo_mcp/staking/models.py
celo_mcp/staking/service.py
celo_mcp/tokens/__init__.py
celo_mcp/tokens/models.py
celo_mcp/tokens/service.py
celo_mcp/transactions/__init__.py
celo_mcp/transactions/models.py
celo_mcp/transactions/service.py
celo_mcp/utils/__init__.py
celo_mcp/utils/formatting.py
celo_mcp/utils/logging.py
celo_mcp/utils/multicall.py
celo_mcp/utils/multicall3.json
celo_mcp/utils/validators.py
celo_mcp-0.3.2.dist-info/METADATA
celo_mcp-0.3.2.dist-info/WHEEL
celo_mcp-0.3.2.dist-info/entry_points.txt
celo_mcp-0.3.2.dist-info/licenses/LICENSE
celo_mcp-0.3.2.dist-info/RECORD
