Metadata-Version: 2.4
Name: celo_mcp
Version: 0.3.2
Summary: A Model Context Protocol (MCP) server for Celo blockchain data access and functionality
Project-URL: Homepage, https://github.com/viral-sangani/celo-mcp
Project-URL: Repository, https://github.com/viral-sangani/celo-mcp
Project-URL: Documentation, https://github.com/viral-sangani/celo-mcp#readme
Project-URL: Issues, https://github.com/viral-sangani/celo-mcp/issues
Author-email: viral-sangani <viral.sangani2011@gmail.com>
License-File: LICENSE
Keywords: ai,blockchain,celo,llm,mcp,web3
Classifier: Development Status :: 3 - Alpha
Classifier: Intended Audience :: Developers
Classifier: License :: OSI Approved :: MIT License
Classifier: Programming Language :: Python :: 3
Requires-Python: >=3.11
Requires-Dist: asyncio-throttle>=1.0.0
Requires-Dist: crawl4ai>=0.6.0
Requires-Dist: eth-abi>=5.0.0
Requires-Dist: eth-account>=0.11.0
Requires-Dist: eth-utils>=4.0.0
Requires-Dist: httpx>=0.27.0
Requires-Dist: mcp>=1.2.0
Requires-Dist: pydantic>=2.0.0
Requires-Dist: python-dotenv>=1.0.0
Requires-Dist: pyyaml>=6.0.0
Requires-Dist: requests>=2.31.0
Requires-Dist: urllib3>=2.0.0
Requires-Dist: web3>=7.0.0
Provides-Extra: dev
Requires-Dist: black>=24.0.0; extra == 'dev'
Requires-Dist: mypy>=1.8.0; extra == 'dev'
Requires-Dist: pre-commit>=3.6.0; extra == 'dev'
Requires-Dist: pytest-asyncio>=0.23.0; extra == 'dev'
Requires-Dist: pytest>=8.0.0; extra == 'dev'
Requires-Dist: ruff>=0.1.0; extra == 'dev'
